{"s": "Cerbera inflata", "c": "['AU']", "n": ["161624417", "207275596", "207275614", "207275124", "165491378", "165491400", "165702217", "165702257", "252988255", "175244821"], "r": ["Rene", "Nancy Holcroft Benson", "Nancy Holcroft Benson", "Nancy Holcroft Benson", "Matthew Borella", "Matthew Borella", "Matthew Borella", "Matthew Borella", "Pete Woodall", "Matthew Borella"], "l": ["CC BY-NC 4.0", "CC BY-NC 4.0", "CC BY-NC 4.0", "CC BY-NC 4.0", "CC BY 4.0", "CC BY 4.0", "CC BY 4.0", "CC BY 4.0", "CC BY-NC 4.0", "CC BY 4.0"], "i": ["jpeg", "jpeg", "jpeg", "jpeg", "jpeg", "jpeg", "jpeg", "jpeg", "jpeg", "jpeg"]}