{"s": "Dahlia apiculata", "c": "['MX']", "n": ["2779663", "292031277", "292031256", "292031300", "5287843", "7963611", "8979887", "20362758", "109520988", "151889633"], "r": ["Leticia Soriano Flores", "Jes\u00fas G. Gonz\u00e1lez Gallegos", "Jes\u00fas G. Gonz\u00e1lez Gallegos", "Jes\u00fas G. Gonz\u00e1lez Gallegos", "Neptal\u00ed Ram\u00edrez Marcial", "Tepelmeme Villa de Morelos", "Fernando Bautista", "geomanuel", "Patricia Hern\u00e1ndez", "Leticia Soriano Flores"], "l": ["CC BY-NC 4.0", "CC BY-NC 4.0", "CC BY-NC 4.0", "CC BY-NC 4.0", "CC BY 4.0", "CC BY-NC 4.0", "CC BY 4.0", "CC BY-NC 4.0", "CC BY-NC 4.0", "CC BY-NC 4.0"], "i": ["JPG", "jpeg", "jpeg", "jpeg", "jpeg", "jpeg", "jpeg", "jpeg", "jpeg", "jpeg"]}