{"s": "Asclepias meadii", "c": "['US']", "n": ["198515610", "198515641", "198515669", "284992728", "284992759", "284992795", "459210", "286011103", "286011123", "286208659"], "r": ["brettbudach", "brettbudach", "brettbudach", "nherbison1203", "nherbison1203", "nherbison1203", "Kenneth Bader", "brettbudach", "brettbudach", "Tom Radocy"], "l": ["CC BY-NC 4.0", "CC BY-NC 4.0", "CC BY-NC 4.0", "CC BY-NC 4.0", "CC BY-NC 4.0", "CC BY-NC 4.0", "CC BY-NC 4.0", "CC BY-NC 4.0", "CC BY-NC 4.0", "CC BY-NC 4.0"], "i": ["jpg", "jpg", "jpg", "jpg", "jpg", "jpg", "JPG", "jpg", "jpg", "jpeg"]}