{"s": "Collomia tenella", "c": "['US']", "n": ["74753671", "74753721", "74753620", "74753772", "198968080", "202059253", "202059267", "205649488", "205827835", "205649530"], "r": ["Nolan Exe", "Nolan Exe", "Nolan Exe", "Nolan Exe", "Walter Fertig", "Laura Holloway", "Laura Holloway", "julegust", "julegust", "julegust"], "l": ["CC BY 4.0", "CC BY 4.0", "CC BY 4.0", "CC BY 4.0", "CC BY-NC 4.0", "CC0 1.0", "CC0 1.0", "CC BY-NC 4.0", "CC BY-NC 4.0", "CC BY-NC 4.0"], "i": ["jpeg", "jpeg", "jpeg", "jpeg", "jpg", "jpg", "jpg", "jpeg", "jpeg", "jpeg"]}