{"s": "Aizoanthemopsis hispanica", "c": "['ES', 'CY', 'IR', 'PT', 'IL', 'IQ', 'KW', 'DZ', 'SA', 'MA', 'PS']", "n": ["114652308", "114652408", "114652478", "114652524", "114652587", "114652634", "114652660", "114652688", "198581015", "198581027"], "r": ["abedalsalam", "abedalsalam", "abedalsalam", "abedalsalam", "abedalsalam", "abedalsalam", "abedalsalam", "abedalsalam", "Javier Peralta de Andr\u00e9s", "Javier Peralta de Andr\u00e9s"], "l": ["CC BY-NC 4.0", "CC BY-NC 4.0", "CC BY-NC 4.0", "CC BY-NC 4.0", "CC BY-NC 4.0", "CC BY-NC 4.0", "CC BY-NC 4.0", "CC BY-NC 4.0", "CC BY-NC 4.0", "CC BY-NC 4.0"], "i": ["jpg", "jpg", "jpg", "jpg", "jpg", "jpg", "jpg", "jpg", "jpeg", "jpeg"]}