{"s": "Dicoria canescens", "c": "['MX', 'US']", "n": ["241446950", "36789852", "285398216", "37220737", "242409556", "37477120", "242501198", "116252959", "116252965", "116252974"], "r": ["Avery Hansen", "Rod", "Jim Andre", "Chris Evers", "Fred Melgert / Carla Hoegen", "Don Rideout", "Avery Hansen", "Bob Miller", "Bob Miller", "Bob Miller"], "l": ["CC BY-NC 4.0", "CC0 1.0", "CC BY-NC 4.0", "CC BY-NC 4.0", "CC BY-NC 4.0", "CC BY-NC 4.0", "CC BY-NC 4.0", "CC BY 4.0", "CC BY 4.0", "CC BY 4.0"], "i": ["jpg", "jpeg", "jpeg", "jpg", "jpg", "jpg", "jpg", "jpeg", "jpeg", "jpeg"]}