{"s": "Aspalathus spinosa", "c": "['ZA']", "n": ["241553729", "241553794", "241553817", "241553767", "75018525", "75018366", "75018242", "75018092", "37052904", "37052721"], "r": ["Karol Cameron", "Karol Cameron", "Karol Cameron", "Karol Cameron", "Dave U", "Dave U", "Dave U", "Dave U", "Carina Lochner", "Carina Lochner"], "l": ["CC BY-NC 4.0", "CC BY-NC 4.0", "CC BY-NC 4.0", "CC BY-NC 4.0", "CC BY 4.0", "CC BY 4.0", "CC BY 4.0", "CC BY 4.0", "CC BY-NC 4.0", "CC BY-NC 4.0"], "i": ["jpeg", "jpeg", "jpeg", "jpeg", "jpg", "jpg", "jpg", "jpg", "jpg", "jpg"]}