{"s": "Manfreda longiflora", "c": "['MX', 'US']", "n": ["284597777", "246343325", "246642710", "246642712", "246642717", "246642718", "246642721", "246642724", "5504503", "14504448"], "r": ["Reid Hardin", "Alexis L\u00f3pez Hern\u00e1ndez", "Alexis L\u00f3pez Hern\u00e1ndez", "Alexis L\u00f3pez Hern\u00e1ndez", "Alexis L\u00f3pez Hern\u00e1ndez", "Alexis L\u00f3pez Hern\u00e1ndez", "Alexis L\u00f3pez Hern\u00e1ndez", "Alexis L\u00f3pez Hern\u00e1ndez", "Miguel", "Matushka Elizabeth Perdomo"], "l": ["CC BY-NC 4.0", "CC BY 4.0", "CC BY 4.0", "CC BY 4.0", "CC BY 4.0", "CC BY 4.0", "CC BY 4.0", "CC BY 4.0", "CC BY-NC 4.0", "CC BY-NC 4.0"], "i": ["jpeg", "jpeg", "jpeg", "jpeg", "jpeg", "jpeg", "jpeg", "jpeg", "jpeg", "jpeg"]}