{"s": "Leptinella nana", "c": "['NZ']", "n": ["157663981", "1314057", "1314058", "1314059", "1314060", "1314062", "1314063", "1314064", "1314065", "1314066"], "r": ["Aalbert Rebergen", "Jon Sullivan", "Jon Sullivan", "Jon Sullivan", "Jon Sullivan", "Jon Sullivan", "Jon Sullivan", "Jon Sullivan", "Jon Sullivan", "Jon Sullivan"], "l": ["CC BY 4.0", "CC BY 4.0", "CC BY 4.0", "CC BY 4.0", "CC BY 4.0", "CC BY 4.0", "CC BY 4.0", "CC BY 4.0", "CC BY 4.0", "CC BY 4.0"], "i": ["jpeg", "jpg", "jpg", "jpg", "jpg", "jpg", "jpg", "jpg", "jpg", "jpg"]}