{"s": "Delphinium depauperatum", "c": "['US']", "n": ["201383468", "201383497", "201383525", "46458370", "86025224", "86025244", "86025257", "130753032", "215897207", "134967245"], "r": ["Remington Jackson", "Remington Jackson", "Remington Jackson", "David Greenberger", "subhashc", "subhashc", "subhashc", "Drew Meyer", "Regina Johnson", "mhays"], "l": ["CC BY-NC 4.0", "CC BY-NC 4.0", "CC BY-NC 4.0", "CC BY-NC-ND 4.0", "CC BY-NC 4.0", "CC BY-NC 4.0", "CC BY-NC 4.0", "CC BY-NC 4.0", "CC BY-NC 4.0", "CC BY-NC 4.0"], "i": ["jpg", "jpg", "jpg", "jpeg", "jpeg", "jpeg", "jpeg", "jpeg", "jpeg", "jpeg"]}