{"s": "Pelargonium mollicomum", "c": "['ZA']", "n": ["214996894", "214996940", "214996991", "106934939", "106935034", "106935059", "106935078", "106935082", "106935101", "106935098"], "r": ["Felix Riegel", "Felix Riegel", "Felix Riegel", "Craig Peter", "Craig Peter", "Craig Peter", "Craig Peter", "Craig Peter", "Craig Peter", "Craig Peter"], "l": ["CC BY-NC 4.0", "CC BY-NC 4.0", "CC BY-NC 4.0", "CC BY-NC 4.0", "CC BY-NC 4.0", "CC BY-NC 4.0", "CC BY-NC 4.0", "CC BY-NC 4.0", "CC BY-NC 4.0", "CC BY-NC 4.0"], "i": ["jpeg", "jpeg", "jpeg", "jpeg", "jpeg", "jpeg", "jpeg", "jpeg", "jpeg", "jpeg"]}