{"s": "Moraea minima", "c": "['ZA']", "n": ["224484623", "224484660", "323514328", "323514325", "323514329", "323514385", "323514389", "323514395", "323514398", "323514402"], "r": ["Eugene Hahndiek", "Eugene Hahndiek", "Hafeez Sonday", "Hafeez Sonday", "Hafeez Sonday", "Hafeez Sonday", "Hafeez Sonday", "Hafeez Sonday", "Hafeez Sonday", "Hafeez Sonday"], "l": ["CC BY-NC 4.0", "CC BY-NC 4.0", "CC BY-NC 4.0", "CC BY-NC 4.0", "CC BY-NC 4.0", "CC BY-NC 4.0", "CC BY-NC 4.0", "CC BY-NC 4.0", "CC BY-NC 4.0", "CC BY-NC 4.0"], "i": ["jpeg", "jpeg", "jpeg", "jpeg", "jpeg", "jpeg", "jpeg", "jpeg", "jpeg", "jpeg"]}