{"s": "Ananas macrodontes", "c": "['BR', 'AR']", "n": ["114781051", "320583918", "242108515", "242108540", "242108556", "244305842", "244305876", "244305864", "77715217", "2728906"], "r": ["Thomaz Ricardo Favreto Sinani", "Thomaz Ricardo Favreto Sinani", "Paul Tavares", "Paul Tavares", "Paul Tavares", "Leonel Roget", "Leonel Roget", "Leonel Roget", "maurieres", "Nicolas Olejnik"], "l": ["CC BY-NC 4.0", "CC BY-NC 4.0", "CC BY-NC 4.0", "CC BY-NC 4.0", "CC BY-NC 4.0", "CC BY 4.0", "CC BY 4.0", "CC BY 4.0", "CC BY-NC 4.0", "CC BY-NC 4.0"], "i": ["jpeg", "jpg", "jpg", "jpg", "jpg", "jpeg", "jpeg", "jpeg", "jpg", "jpg"]}