{"s": "Empogona lanceolata", "c": "['ZA', 'SZ']", "n": ["284991865", "242642022", "242642028", "242642031", "243537165", "243537209", "243537260", "244352677", "244362765", "244362746"], "r": ["Reuben Heydenrych", "Mahomed Desai", "Mahomed Desai", "Mahomed Desai", "Marilize", "Marilize", "Marilize", "Reuben Heydenrych", "Reuben Heydenrych", "Reuben Heydenrych"], "l": ["CC BY-NC 4.0", "CC BY 4.0", "CC BY 4.0", "CC BY 4.0", "CC BY-NC 4.0", "CC BY-NC 4.0", "CC BY-NC 4.0", "CC BY-NC 4.0", "CC BY-NC 4.0", "CC BY-NC 4.0"], "i": ["jpg", "jpeg", "jpeg", "jpeg", "jpeg", "jpeg", "jpeg", "jpg", "jpg", "jpg"]}