{"s": "Coleogyne ramosissima", "c": "['US']", "n": ["36408693", "36411955", "36412148", "36412054", "198498372", "198498393", "198498415", "284742781", "198539742", "166302"], "r": ["Elize Van Zandt", "larry-heronema", "larry-heronema", "larry-heronema", "amandabarth82", "amandabarth82", "amandabarth82", "Roland Godon", "elenapalkaflores", "J Brew"], "l": ["CC BY-NC 4.0", "CC BY-NC 4.0", "CC BY-NC 4.0", "CC BY-NC 4.0", "CC BY-NC 4.0", "CC BY-NC 4.0", "CC BY-NC 4.0", "CC BY 4.0", "CC BY-NC 4.0", "CC BY-SA 4.0"], "i": ["jpg", "jpg", "jpg", "jpg", "jpeg", "jpeg", "jpeg", "jpeg", "jpeg", "jpg"]}