{"s": "Grevillea stenobotrya", "c": "['AU']", "n": ["157020783", "243342951", "247017300", "247017312", "247017329", "247017353", "44081249", "44081252", "44081258", "88993333"], "r": ["Sue Jaggar", "Euan Moore", "Tom Hunt", "Tom Hunt", "Tom Hunt", "Tom Hunt", "Ray Turnbull", "Ray Turnbull", "Ray Turnbull", "dhfischer"], "l": ["CC BY-NC-ND 4.0", "CC BY-NC 4.0", "CC BY-NC 4.0", "CC BY-NC 4.0", "CC BY-NC 4.0", "CC BY-NC 4.0", "CC BY-NC 4.0", "CC BY-NC 4.0", "CC BY-NC 4.0", "CC BY-NC 4.0"], "i": ["jpg", "jpeg", "jpg", "jpg", "jpg", "jpg", "jpg", "jpg", "jpg", "jpg"]}