{"s": "Carex brownii", "c": "['KR', 'AU']", "n": ["243972449", "243972496", "243972539", "243972570", "4204529", "4217402", "4217404", "241139866", "241141574", "241141590"], "r": ["Darren Fielder", "Darren Fielder", "Darren Fielder", "Darren Fielder", "Lee", "seong-won", "Lee", "seong-won", "Lee", "seong-won"], "l": ["CC BY-NC 4.0", "CC BY-NC 4.0", "CC BY-NC 4.0", "CC BY-NC 4.0", "CC BY-NC 4.0", "CC BY-NC 4.0", "CC BY-NC 4.0", "CC BY-NC 4.0", "CC BY-NC 4.0", "CC BY-NC 4.0"], "i": ["jpeg", "jpeg", "jpeg", "jpeg", "jpg", "jpg", "jpg", "jpeg", "jpeg", "jpeg"]}