{"s": "Euphorbia pyrenaica", "c": "['FR', 'ES']", "n": ["201705903", "205533903", "205533979", "205533981", "205534001", "164940439", "303584667", "303584711", "303584638", "303584684"], "r": ["fermin_y_ana", "Jorge Calvo Yuste", "Jorge Calvo Yuste", "Jorge Calvo Yuste", "Jorge Calvo Yuste", "fermin_y_ana", "Sylvain Piry", "Sylvain Piry", "Sylvain Piry", "Sylvain Piry"], "l": ["CC BY-NC 4.0", "CC BY-NC 4.0", "CC BY-NC 4.0", "CC BY-NC 4.0", "CC BY-NC 4.0", "CC BY-NC 4.0", "CC BY-NC 4.0", "CC BY-NC 4.0", "CC BY-NC 4.0", "CC BY-NC 4.0"], "i": ["jpeg", "jpg", "jpg", "jpg", "jpg", "jpeg", "jpeg", "jpeg", "jpeg", "jpeg"]}