{"s": "Cupressus revealiana", "c": "['MX']", "n": ["5547056", "5547258", "12043888", "263608896", "263608849", "182165147", "182165154", "182165161", "182167156", "182167163"], "r": ["Joey Santore", "Joey Santore", "Joey Santore", "Cristian A. D. Meling L.", "Cristian A. D. Meling L.", "Carlos Gonzalez", "Carlos Gonzalez", "Carlos Gonzalez", "Carlos Gonzalez", "Carlos Gonzalez"], "l": ["CC BY-NC 4.0", "CC BY-NC 4.0", "CC BY-NC 4.0", "CC BY-NC-SA 4.0", "CC BY-NC-SA 4.0", "CC BY-NC 4.0", "CC BY-NC 4.0", "CC BY-NC 4.0", "CC BY-NC 4.0", "CC BY-NC 4.0"], "i": ["jpeg", "jpeg", "jpeg", "jpeg", "jpeg", "jpg", "jpg", "jpg", "jpg", "jpg"]}