{"s": "Xylopia macrantha", "c": "['PA']", "n": ["75786740", "52536365", "55309157", "55309162", "55309161", "56226358", "56226367", "61931107", "61931106", "61931086"], "r": ["Jens-Christian Svenning", "Letizia Weichgrebe", "Letizia Weichgrebe", "Letizia Weichgrebe", "Letizia Weichgrebe", "Letizia Weichgrebe", "Letizia Weichgrebe", "Letizia Weichgrebe", "Letizia Weichgrebe", "Letizia Weichgrebe"], "l": ["CC BY 4.0", "CC BY-NC 4.0", "CC BY-NC 4.0", "CC BY-NC 4.0", "CC BY-NC 4.0", "CC BY-NC 4.0", "CC BY-NC 4.0", "CC BY-NC 4.0", "CC BY-NC 4.0", "CC BY-NC 4.0"], "i": ["jpeg", "jpeg", "jpeg", "jpeg", "jpeg", "jpeg", "jpeg", "jpeg", "jpeg", "jpeg"]}