{"s": "Ligularia sachalinensis", "c": "['RU']", "n": ["295571359", "45721055", "45721089", "45721255", "45721278", "46355730", "176126226", "176126253", "176126276", "221158991"], "r": ["V.S. Volkotrub", "Ilya Bogachyov", "Ilya Bogachyov", "Ilya Bogachyov", "Ilya Bogachyov", "Gularjanz Grigoryi Mihajlovich", "Vladimir Yu. Arkhipov", "Vladimir Yu. Arkhipov", "Vladimir Yu. Arkhipov", "Vladimir Yu. Arkhipov"], "l": ["CC BY-NC 4.0", "CC BY-NC 4.0", "CC BY-NC 4.0", "CC BY-NC 4.0", "CC BY-NC 4.0", "CC BY-NC 4.0", "CC BY-NC 4.0", "CC BY-NC 4.0", "CC BY-NC 4.0", "CC BY-NC 4.0"], "i": ["jpeg", "jpeg", "jpeg", "jpeg", "jpeg", "jpeg", "jpeg", "jpeg", "jpeg", "jpeg"]}