{"s": "Eryngium venustum", "c": "['MX']", "n": ["472999", "473005", "473006", "882815", "944540", "947390", "6108154", "6108156", "226973570", "226973580"], "r": ["Carlos G Velazco-Macias", "Carlos G Velazco-Macias", "Carlos G Velazco-Macias", "Carlos G Velazco-Macias", "Carlos G Velazco-Macias", "Carlos G Velazco-Macias", "Carlos G Velazco-Macias", "Carlos G Velazco-Macias", "Carlos G Velazco-Macias", "Carlos G Velazco-Macias"], "l": ["CC BY-NC 4.0", "CC BY-NC 4.0", "CC BY-NC 4.0", "CC BY-NC 4.0", "CC BY-NC 4.0", "CC BY-NC 4.0", "CC BY-NC 4.0", "CC BY-NC 4.0", "CC BY-NC 4.0", "CC BY-NC 4.0"], "i": ["JPG", "JPG", "JPG", "JPG", "JPG", "JPG", "jpeg", "jpeg", "jpeg", "jpeg"]}