{"s": "Sommera arborescens", "c": "['MX']", "n": ["172452897", "172452892", "172452886", "172452881", "172452906", "172452912", "172452918", "172452925", "12350339"], "r": ["Esteban Marinero Sobal", "Esteban Marinero Sobal", "Esteban Marinero Sobal", "Esteban Marinero Sobal", "Esteban Marinero Sobal", "Esteban Marinero Sobal", "Esteban Marinero Sobal", "Esteban Marinero Sobal", "Neptal\u00ed Ram\u00edrez Marcial"], "l": ["CC BY-NC 4.0", "CC BY-NC 4.0", "CC BY-NC 4.0", "CC BY-NC 4.0", "CC BY-NC 4.0", "CC BY-NC 4.0", "CC BY-NC 4.0", "CC BY-NC 4.0", "CC BY 4.0"], "i": ["jpg", "jpg", "jpg", "jpg", "jpg", "jpg", "jpg", "jpg", "jpg"]}