{"s": "Goniopteris hastata", "c": "['PR']", "n": ["293281111", "293281157", "293281190", "312834533", "312834552", "312834569", "150573460", "150577229"], "r": ["Omar Monzon Carmona", "Omar Monzon Carmona", "Omar Monzon Carmona", "Omar Monzon Carmona", "Omar Monzon Carmona", "Omar Monzon Carmona", "Jennifer Possley", "Jennifer Possley"], "l": ["CC BY-NC 4.0", "CC BY-NC 4.0", "CC BY-NC 4.0", "CC BY-NC 4.0", "CC BY-NC 4.0", "CC BY-NC 4.0", "CC BY-NC 4.0", "CC BY-NC 4.0"], "i": ["jpg", "jpg", "jpg", "jpg", "jpg", "jpg", "jpg", "jpg"]}