{"s": "Consolea picardae", "c": "['HT', 'DO']", "n": ["253309373", "211621967", "211621999", "211621939", "211622040", "211622082", "211622116", "32876314", "32876310", "32876326"], "r": ["gabriellugo", "Daniel S. Cooper", "Daniel S. Cooper", "Daniel S. Cooper", "Daniel S. Cooper", "Daniel S. Cooper", "Daniel S. Cooper", "Martin Reith", "Martin Reith", "Martin Reith"], "l": ["CC BY-NC 4.0", "CC BY-NC 4.0", "CC BY-NC 4.0", "CC BY-NC 4.0", "CC BY-NC 4.0", "CC BY-NC 4.0", "CC BY-NC 4.0", "CC BY-NC 4.0", "CC BY-NC 4.0", "CC BY-NC 4.0"], "i": ["jpg", "jpg", "jpg", "jpg", "jpg", "jpg", "jpg", "jpeg", "jpeg", "jpeg"]}