{"s": "Plantago heterophylla", "c": "['US']", "n": ["37075933", "37075994", "117518389", "117518416", "3232772", "3232773", "3232774", "3794415", "3794418", "122394326"], "r": ["Sam Kieschnick", "Sam Kieschnick", "Sam Kieschnick", "Sam Kieschnick", "Sam Kieschnick", "Sam Kieschnick", "Sam Kieschnick", "\"Bob OKennon\"", "\"Bob OKennon\"", "johntownsend"], "l": ["CC BY 4.0", "CC BY 4.0", "CC BY 4.0", "CC BY 4.0", "CC BY 4.0", "CC BY 4.0", "CC BY 4.0", "CC BY-NC 4.0", "CC BY-NC 4.0", "CC BY-NC 4.0"], "i": ["jpg", "jpg", "jpeg", "jpeg", "JPG", "JPG", "JPG", "jpg", "jpg", "jpg"]}