{"s": "Arachniodes denticulata", "c": "['CR', 'BO', 'CO', 'PE', 'MX']", "n": ["79200732", "79200591", "3836112", "83222086", "83222814", "126731467", "126731404", "12068380", "12068384", "93710608"], "r": ["humbertomendozacifuentes", "humbertomendozacifuentes", "Lena Struwe", "William Bravo", "William Bravo", "Ana Maria Benavides", "Ana Maria Benavides", "Nate Hartley", "Nate Hartley", "Roberto Chavarro Ch\u00e1varro"], "l": ["CC BY-NC 4.0", "CC BY-NC 4.0", "CC BY-SA 4.0", "CC BY-NC 4.0", "CC BY-NC 4.0", "CC BY-NC 4.0", "CC BY-NC 4.0", "CC BY-NC 4.0", "CC BY-NC 4.0", "CC BY-NC 4.0"], "i": ["jpg", "jpg", "JPG", "jpeg", "jpeg", "jpeg", "jpeg", "jpeg", "jpeg", "jpeg"]}