{"s": "Selaginella falcata", "c": "['GF']", "n": ["301044655", "301044615", "301044992", "301045367", "301045171", "260930922", "260931086", "260931143", "178686772", "178686966"], "r": ["Julien Piolain", "Julien Piolain", "Julien Piolain", "Julien Piolain", "Julien Piolain", "Robin Heymans", "Robin Heymans", "Robin Heymans", "S\u00e9bastien SANT", "S\u00e9bastien SANT"], "l": ["CC BY-NC 4.0", "CC BY-NC 4.0", "CC BY-NC 4.0", "CC BY-NC 4.0", "CC BY-NC 4.0", "CC BY-NC 4.0", "CC BY-NC 4.0", "CC BY-NC 4.0", "CC BY-NC 4.0", "CC BY-NC 4.0"], "i": ["jpg", "jpg", "jpg", "jpg", "jpg", "jpeg", "jpeg", "jpeg", "jpeg", "jpeg"]}