{"s": "Trifolium angustifolium", "c": "['US', 'GR', 'NZ', 'RU', 'AL', 'TR', 'AU', 'HR', 'AZ', 'ME', 'ES', 'IL', 'DZ', 'ZA', 'BE', 'BA', 'UA', 'CY', 'PT', 'AM', 'FR', 'BG', 'GE', 'CL', 'IT']", "n": ["284550037", "284550084", "284550110", "284550155", "74517813", "74517846", "155836319", "198398492", "36399981", "36400050"], "r": ["Garth Harwood", "Garth Harwood", "Garth Harwood", "Garth Harwood", "Pedro Andrade", "Pedro Andrade", "\u00c1ngel Fern\u00e1ndez Cancio", "Jurga Motiej\u016bnait\u0117", "julianclark", "julianclark"], "l": ["CC BY 4.0", "CC BY 4.0", "CC BY 4.0", "CC BY 4.0", "CC BY-NC 4.0", "CC BY-NC 4.0", "CC BY-NC 4.0", "CC BY-NC 4.0", "CC BY-NC 4.0", "CC BY-NC 4.0"], "i": ["jpeg", "jpeg", "jpeg", "jpeg", "jpeg", "jpeg", "jpg", "jpeg", "jpg", "jpg"]}