{"s": "Viburnum erosum", "c": "['CN', 'JP', 'KR', 'TW']", "n": ["115532365", "38555182", "38555188", "38555186", "38555190", "244042198", "40118992", "289333453", "289333434", "289333478"], "r": ["\u773c\u5b50\u83dc", "Mizuki Shimoda", "Mizuki Shimoda", "Mizuki Shimoda", "Mizuki Shimoda", "\u308a\u306a\u3079\u308b", "harum.koh", "gordon901228", "gordon901228", "gordon901228"], "l": ["CC BY-NC 4.0", "CC BY-NC 4.0", "CC BY-NC 4.0", "CC BY-NC 4.0", "CC BY-NC 4.0", "CC BY-NC 4.0", "CC BY-SA 4.0", "CC BY-NC 4.0", "CC BY-NC 4.0", "CC BY-NC 4.0"], "i": ["jpeg", "jpg", "jpg", "jpg", "jpg", "jpg", "jpeg", "jpeg", "jpeg", "jpeg"]}