{"s": "Phlebodium pseudoaureum", "c": "['PR', 'US', 'JM', 'VI', 'SV', 'EC', 'CR', 'VE', 'DO', 'PA', 'NI', 'CO', 'MX', 'HN']", "n": ["241446153", "241446158", "241446220", "156216749", "156216778", "156216834", "156216857", "156216865", "156216874", "156216765"], "r": ["Diego Alfonso Ruiz Cordero", "Diego Alfonso Ruiz Cordero", "Diego Alfonso Ruiz Cordero", "mvz-juangonzalezromero", "mvz-juangonzalezromero", "mvz-juangonzalezromero", "mvz-juangonzalezromero", "mvz-juangonzalezromero", "mvz-juangonzalezromero", "mvz-juangonzalezromero"], "l": ["CC BY-NC 4.0", "CC BY-NC 4.0", "CC BY-NC 4.0", "CC BY-NC 4.0", "CC BY-NC 4.0", "CC BY-NC 4.0", "CC BY-NC 4.0", "CC BY-NC 4.0", "CC BY-NC 4.0", "CC BY-NC 4.0"], "i": ["jpg", "jpg", "jpg", "jpeg", "jpeg", "jpeg", "jpeg", "jpeg", "jpeg", "jpeg"]}