{"s": "Melica spectabilis", "c": "['US']", "n": ["4137812", "4201300", "222822904", "222822945", "222822970", "222823005", "222823035", "222823066", "222823102", "222823140"], "r": ["Hilary Rose Dawson", "Hilary Rose Dawson", "Luis Lopez-Contreras", "Luis Lopez-Contreras", "Luis Lopez-Contreras", "Luis Lopez-Contreras", "Luis Lopez-Contreras", "Luis Lopez-Contreras", "Luis Lopez-Contreras", "Luis Lopez-Contreras"], "l": ["CC BY-NC-SA 4.0", "CC BY-NC-SA 4.0", "CC BY-NC 4.0", "CC BY-NC 4.0", "CC BY-NC 4.0", "CC BY-NC 4.0", "CC BY-NC 4.0", "CC BY-NC 4.0", "CC BY-NC 4.0", "CC BY-NC 4.0"], "i": ["jpg", "jpg", "jpeg", "jpeg", "jpeg", "jpeg", "jpeg", "jpeg", "jpeg", "jpeg"]}