{"s": "Gastrolobium praemorsum", "c": "['AU']", "n": ["156637717", "156638237", "156638313", "156638386", "160619697", "160619709", "160619722", "167360342", "167360350", "167360357"], "r": ["Chris Jonkers", "Chris Jonkers", "Chris Jonkers", "Chris Jonkers", "gdaydanae", "gdaydanae", "gdaydanae", "Caroline Telfer", "Caroline Telfer", "Caroline Telfer"], "l": ["CC BY-NC 4.0", "CC BY-NC 4.0", "CC BY-NC 4.0", "CC BY-NC 4.0", "CC BY-NC 4.0", "CC BY-NC 4.0", "CC BY-NC 4.0", "CC BY-NC 4.0", "CC BY-NC 4.0", "CC BY-NC 4.0"], "i": ["jpeg", "jpeg", "jpeg", "jpeg", "jpeg", "jpeg", "jpeg", "jpeg", "jpeg", "jpeg"]}