{"s": "Grewia hispida", "c": "['ZA']", "n": ["201038721", "172671512", "172671525", "172956101", "172956119", "172956129", "15163752", "15163753", "59507773", "59507852"], "r": ["Gail Bowers-Winters", "Anthony Walton", "Anthony Walton", "Alison Young", "Alison Young", "Alison Young", "lizziepop", "lizziepop", "Peter Warren", "Peter Warren"], "l": ["CC BY-NC 4.0", "CC BY-NC 4.0", "CC BY-NC 4.0", "CC BY-NC 4.0", "CC BY-NC 4.0", "CC BY-NC 4.0", "CC BY-NC 4.0", "CC BY-NC 4.0", "CC0 1.0", "CC0 1.0"], "i": ["jpg", "jpg", "jpg", "jpeg", "jpeg", "jpeg", "jpg", "jpg", "jpeg", "jpeg"]}