{"s": "Euploca pringlei", "c": "['MX']", "n": ["246646536", "246647184", "246646542", "246647222", "246647223", "246646545", "246647243", "9362615", "9362616", "9362622"], "r": ["Alexis L\u00f3pez Hern\u00e1ndez", "Alexis L\u00f3pez Hern\u00e1ndez", "Alexis L\u00f3pez Hern\u00e1ndez", "Alexis L\u00f3pez Hern\u00e1ndez", "Alexis L\u00f3pez Hern\u00e1ndez", "Alexis L\u00f3pez Hern\u00e1ndez", "Alexis L\u00f3pez Hern\u00e1ndez", "Diego", "Diego", "Diego"], "l": ["CC BY 4.0", "CC BY 4.0", "CC BY 4.0", "CC BY 4.0", "CC BY 4.0", "CC BY 4.0", "CC BY 4.0", "CC BY-NC 4.0", "CC BY-NC 4.0", "CC BY-NC 4.0"], "i": ["jpeg", "jpeg", "jpeg", "jpeg", "jpeg", "jpeg", "jpeg", "jpeg", "jpeg", "jpeg"]}