{"s": "Babiana crispa", "c": "['ZA']", "n": ["88176510", "219899003", "219898799", "219899188", "219899439", "219899750", "15139277", "15155510", "15155511", "137591584"], "r": ["James Deacon", "Alan Horstmann", "Alan Horstmann", "Alan Horstmann", "Alan Horstmann", "Alan Horstmann", "Patrick Lane", "Alan Horstmann", "Alan Horstmann", "jonclark57"], "l": ["CC BY-NC 4.0", "CC BY-NC 4.0", "CC BY-NC 4.0", "CC BY-NC 4.0", "CC BY-NC 4.0", "CC BY-NC 4.0", "CC BY-NC 4.0", "CC BY-NC 4.0", "CC BY-NC 4.0", "CC BY-NC 4.0"], "i": ["jpeg", "jpeg", "jpeg", "jpeg", "jpeg", "jpeg", "jpg", "jpg", "jpg", "jpg"]}