{"s": "Poa astonii", "c": "['NZ']", "n": ["1203869", "1203876", "1222253", "1239876", "1239895", "1255144", "1299418", "1503044", "1812148", "289100188"], "r": ["Colin Meurk", "Colin Meurk", "John Barkla", "Colin Meurk", "Colin Meurk", "John Barkla", "Sarah Richardson", "sea-kangaroo", "Lisa Bennett", "Alex Fergus"], "l": ["CC BY-SA 4.0", "CC BY-SA 4.0", "CC BY 4.0", "CC BY-SA 4.0", "CC BY-SA 4.0", "CC BY 4.0", "CC BY 4.0", "CC BY-NC-ND 4.0", "CC BY 4.0", "CC BY-NC 4.0"], "i": ["", "", "", "", "", "", "JPG", "JPG", "JPG", "jpg"]}