{"s": "Angelica triquinata", "c": "['US']", "n": ["36412981", "74544046", "74544151", "155884088", "155884114", "155884136", "155884155", "155984098", "155984114", "155994195"], "r": ["jackollis", "Owen Carson", "Owen Carson", "plants_interacting", "plants_interacting", "plants_interacting", "plants_interacting", "kbm56", "kbm56", "lisatabor"], "l": ["CC BY-NC 4.0", "CC BY-NC 4.0", "CC BY-NC 4.0", "CC BY-NC 4.0", "CC BY-NC 4.0", "CC BY-NC 4.0", "CC BY-NC 4.0", "CC BY-NC 4.0", "CC BY-NC 4.0", "CC BY-NC 4.0"], "i": ["jpg", "jpeg", "jpeg", "jpeg", "jpeg", "jpeg", "jpeg", "jpg", "jpg", "jpg"]}