{"s": "Claytonia serpenticola", "c": "['US']", "n": ["75493474", "37744133", "38958852", "201937952", "201938018", "78749203", "120910342", "209420958", "209420940", "47490957"], "r": ["Justin Garwood", "stormcatcher", "stormcatcher", "Christian Schwarz", "Christian Schwarz", "Adrian Macedo", "Jonathan Curley", "Matt Berger", "Matt Berger", "Gail A Baker"], "l": ["CC BY-NC 4.0", "CC BY-NC 4.0", "CC BY-NC 4.0", "CC BY-NC 4.0", "CC BY-NC 4.0", "CC BY-NC 4.0", "CC BY 4.0", "CC BY 4.0", "CC BY 4.0", "CC BY 4.0"], "i": ["jpg", "jpeg", "jpeg", "jpg", "jpg", "jpg", "jpg", "jpeg", "jpeg", "jpeg"]}