{"s": "Blechnum arcuatum", "c": "['CL']", "n": ["243067649", "206429356", "206429381", "251760358", "251760376", "251760387", "211025392", "211025438", "254916336", "254916465"], "r": ["Martin Gardner", "Pablo Silva", "Pablo Silva", "Javian Gallardo Valdivia", "Javian Gallardo Valdivia", "Javian Gallardo Valdivia", "Leonardo Mondaca Lara", "Leonardo Mondaca Lara", "Pablo Silva", "Pablo Silva"], "l": ["CC BY-NC 4.0", "CC BY-NC 4.0", "CC BY-NC 4.0", "CC BY 4.0", "CC BY 4.0", "CC BY 4.0", "CC BY-NC 4.0", "CC BY-NC 4.0", "CC BY-NC 4.0", "CC BY-NC 4.0"], "i": ["jpg", "jpeg", "jpeg", "jpeg", "jpeg", "jpeg", "jpeg", "jpeg", "jpeg", "jpeg"]}