{"s": "Fontainea australis", "c": "['AU']", "n": ["91371096", "91371406", "91371516", "91371692", "91371839", "91371993", "100604110", "100604028", "100604185", "100604154"], "r": ["Lucas G Hopkins", "Lucas G Hopkins", "Lucas G Hopkins", "Lucas G Hopkins", "Lucas G Hopkins", "Lucas G Hopkins", "Lucas G Hopkins", "Lucas G Hopkins", "Lucas G Hopkins", "Lucas G Hopkins"], "l": ["CC BY-NC 4.0", "CC BY-NC 4.0", "CC BY-NC 4.0", "CC BY-NC 4.0", "CC BY-NC 4.0", "CC BY-NC 4.0", "CC BY-NC 4.0", "CC BY-NC 4.0", "CC BY-NC 4.0", "CC BY-NC 4.0"], "i": ["jpeg", "jpeg", "jpeg", "jpeg", "jpeg", "jpeg", "jpeg", "jpeg", "jpeg", "jpeg"]}