{"s": "Liparia calycina", "c": "['ZA']", "n": ["126305532", "126305550", "126316684", "126316714", "126316742", "126317925", "126317992", "126324551", "126324486", "126327537"], "r": ["Tony Rebelo", "Tony Rebelo", "Tony Rebelo", "Tony Rebelo", "Tony Rebelo", "Tony Rebelo", "Tony Rebelo", "Tony Rebelo", "Tony Rebelo", "Tony Rebelo"], "l": ["CC BY-SA 4.0", "CC BY-SA 4.0", "CC BY-SA 4.0", "CC BY-SA 4.0", "CC BY-SA 4.0", "CC BY-SA 4.0", "CC BY-SA 4.0", "CC BY-SA 4.0", "CC BY-SA 4.0", "CC BY-SA 4.0"], "i": ["jpeg", "jpeg", "jpeg", "jpeg", "jpeg", "jpeg", "jpeg", "jpeg", "jpeg", "jpeg"]}