{"s": "Microloma namaquense", "c": "['ZA']", "n": ["209013848", "137400887", "137400913", "137400938", "137400962", "137400974", "137401437", "137401487", "137401512", "137401522"], "r": ["rjq", "Gigi Laidler", "Gigi Laidler", "Gigi Laidler", "Gigi Laidler", "Gigi Laidler", "Gigi Laidler", "Gigi Laidler", "Gigi Laidler", "Gigi Laidler"], "l": ["CC BY-NC 4.0", "CC BY-NC 4.0", "CC BY-NC 4.0", "CC BY-NC 4.0", "CC BY-NC 4.0", "CC BY-NC 4.0", "CC BY-NC 4.0", "CC BY-NC 4.0", "CC BY-NC 4.0", "CC BY-NC 4.0"], "i": ["jpeg", "jpeg", "jpeg", "jpeg", "jpeg", "jpeg", "jpeg", "jpeg", "jpeg", "jpeg"]}