{"s": "Pterostylis flavovirens", "c": "['AU']", "n": ["159791606", "159791611", "159791612", "295583531", "296379139", "298738046", "298738079", "298738075", "298738109", "298738113"], "r": ["Liz", "Liz", "Liz", "Tom Hunt", "JuneN", "distinguished_orca", "distinguished_orca", "distinguished_orca", "distinguished_orca", "distinguished_orca"], "l": ["CC BY-NC 4.0", "CC BY-NC 4.0", "CC BY-NC 4.0", "CC BY-NC 4.0", "CC BY-NC 4.0", "CC BY-NC 4.0", "CC BY-NC 4.0", "CC BY-NC 4.0", "CC BY-NC 4.0", "CC BY-NC 4.0"], "i": ["jpeg", "jpeg", "jpeg", "jpg", "jpg", "jpeg", "jpeg", "jpeg", "jpeg", "jpeg"]}