{"s": "Hilpertia velenovskyi", "c": "['DE']", "n": ["255644281", "255645390", "255645403", "255645405", "255645423", "255645434", "255645439", "255644526", "255645494", "255645500"], "r": ["Stefan Gey", "Stefan Gey", "Stefan Gey", "Stefan Gey", "Stefan Gey", "Stefan Gey", "Stefan Gey", "Stefan Gey", "Stefan Gey", "Stefan Gey"], "l": ["CC BY-NC 4.0", "CC BY-NC 4.0", "CC BY-NC 4.0", "CC BY-NC 4.0", "CC BY-NC 4.0", "CC BY-NC 4.0", "CC BY-NC 4.0", "CC BY-NC 4.0", "CC BY-NC 4.0", "CC BY-NC 4.0"], "i": ["jpeg", "jpeg", "jpeg", "jpeg", "jpeg", "jpeg", "jpeg", "jpeg", "jpeg", "jpeg"]}