{"s": "Miconia cremophylla", "c": "['CO']", "n": ["222606741", "222606641", "222602840", "222603141", "222603228", "222603338", "222603395", "316586850", "316586857", "113726015"], "r": ["Nicol\u00e1s Baresch Uribe", "Nicol\u00e1s Baresch Uribe", "Nicol\u00e1s Baresch Uribe", "Nicol\u00e1s Baresch Uribe", "Nicol\u00e1s Baresch Uribe", "Nicol\u00e1s Baresch Uribe", "Nicol\u00e1s Baresch Uribe", "Nima Gallego", "Nima Gallego", "Apipa"], "l": ["CC BY 4.0", "CC BY 4.0", "CC BY 4.0", "CC BY 4.0", "CC BY 4.0", "CC BY 4.0", "CC BY 4.0", "CC BY-NC 4.0", "CC BY-NC 4.0", "CC BY-NC 4.0"], "i": ["jpg", "jpg", "jpg", "jpg", "jpg", "jpg", "jpg", "jpeg", "jpeg", "jpeg"]}