{"s": "Pavetta hongkongensis", "c": "['CN', 'HK']", "n": ["36543752", "36543764", "36543783", "36543727", "198549892", "198549941", "198549982", "198550038", "198550104", "198550165"], "r": ["ysara", "ysara", "ysara", "ysara", "Alexander M Duggie", "Alexander M Duggie", "Alexander M Duggie", "Alexander M Duggie", "Alexander M Duggie", "Alexander M Duggie"], "l": ["CC BY-NC 4.0", "CC BY-NC 4.0", "CC BY-NC 4.0", "CC BY-NC 4.0", "CC BY-NC 4.0", "CC BY-NC 4.0", "CC BY-NC 4.0", "CC BY-NC 4.0", "CC BY-NC 4.0", "CC BY-NC 4.0"], "i": ["jpg", "jpg", "jpg", "jpg", "jpeg", "jpeg", "jpeg", "jpeg", "jpeg", "jpeg"]}