{"s": "Mammillaria wagneriana", "c": "['MX']", "n": ["284635964", "284636012", "284636062", "284636109", "74970149", "286045390", "286045397", "157165027", "200383624", "38607865"], "r": ["Favian Flores Medina", "Favian Flores Medina", "Favian Flores Medina", "Favian Flores Medina", "josepineda", "Sandra Vargas", "Sandra Vargas", "Heriberto \u00c1vila-Gonz\u00e1lez", "Joseph Scheer", "Chris Lloyd"], "l": ["CC BY-NC 4.0", "CC BY-NC 4.0", "CC BY-NC 4.0", "CC BY-NC 4.0", "CC BY-NC 4.0", "CC BY-NC 4.0", "CC BY-NC 4.0", "CC BY-NC 4.0", "CC BY-NC 4.0", "CC BY-NC 4.0"], "i": ["jpeg", "jpeg", "jpeg", "jpeg", "jpg", "jpeg", "jpeg", "jpg", "jpg", "jpg"]}