{"s": "Cattleya pabstii", "c": "['BR']", "n": ["205974316", "186149083", "186148832", "186148908", "186149065", "186149107", "186149135", "186149156"], "r": ["Miguel A. Casado", "Jake Antonio Heaton", "Jake Antonio Heaton", "Jake Antonio Heaton", "Jake Antonio Heaton", "Jake Antonio Heaton", "Jake Antonio Heaton", "Jake Antonio Heaton"], "l": ["CC BY-NC 4.0", "CC BY-NC 4.0", "CC BY-NC 4.0", "CC BY-NC 4.0", "CC BY-NC 4.0", "CC BY-NC 4.0", "CC BY-NC 4.0", "CC BY-NC 4.0"], "i": ["jpg", "jpeg", "jpeg", "jpeg", "jpeg", "jpeg", "jpeg", "jpeg"]}