{"s": "Ophiopogon japonicus", "c": "['CN', 'ES', 'MY', 'KR', 'US', 'AR', 'FR', 'NZ', 'AU', 'VE', 'TW', 'ZA', 'JP', 'HK', 'IT']", "n": ["36521204", "36521199", "37162945", "115668180", "37633727", "37633738", "117582286", "289755907", "2806095", "203116830"], "r": ["Hiromi kobori", "Hiromi kobori", "deb", "wake_nc", "Yoshihiro Tokue", "Yoshihiro Tokue", "\u767b\u5742\u4e45\u96c4", "\u5468\u5fd7\u548c", "harum.koh", "Mike Young"], "l": ["CC BY-NC 4.0", "CC BY-NC 4.0", "CC BY-NC 4.0", "CC BY-NC 4.0", "CC BY-NC 4.0", "CC BY-NC 4.0", "CC BY-NC 4.0", "CC BY-NC 4.0", "CC BY-SA 4.0", "CC BY-NC 4.0"], "i": ["jpg", "jpg", "jpeg", "jpeg", "jpeg", "jpeg", "jpg", "jpg", "jpg", "jpg"]}