{"s": "Lepidosperma elatius", "c": "['AU']", "n": ["198746816", "74919467", "74919470", "37670021", "37670022", "37670025", "37670430", "37670429", "75701108", "75701067"], "r": ["Reiner Richter", "Chris Clarke", "Chris Clarke", "Wayne Martin", "Wayne Martin", "Wayne Martin", "Wayne Martin", "Wayne Martin", "Reiner Richter", "Reiner Richter"], "l": ["CC BY-NC-SA 4.0", "CC BY 4.0", "CC BY 4.0", "CC BY-NC 4.0", "CC BY-NC 4.0", "CC BY-NC 4.0", "CC BY-NC 4.0", "CC BY-NC 4.0", "CC BY-NC-SA 4.0", "CC BY-NC-SA 4.0"], "i": ["jpeg", "jpeg", "jpeg", "jpeg", "jpeg", "jpeg", "jpeg", "jpeg", "jpeg", "jpeg"]}