{"s": "Loeselia mexicana", "c": "['MX']", "n": ["114597516", "36416464", "241479975", "36592514", "36700006", "36710071", "232227", "236242", "36731323", "36731528"], "r": ["Gaby Gutierrez", "Bodo Nu\u00f1ez Oberg", "Jordi Mart\u00ednez Mart\u00ednez", "ekdelval", "Ignacio Torres Garc\u00eda", "Ignacio Torres Garc\u00eda", "Scott Loarie", "Ken-ichi Ueda", "SIRUKI EDUCACI\u00d3N AMBIENTAL A.C.", "SIRUKI EDUCACI\u00d3N AMBIENTAL A.C."], "l": ["CC BY 4.0", "CC BY-NC 4.0", "CC BY 4.0", "CC BY-NC 4.0", "CC BY-NC 4.0", "CC BY-NC 4.0", "CC0 1.0", "CC BY 4.0", "CC BY-NC 4.0", "CC BY-NC 4.0"], "i": ["jpeg", "jpg", "jpeg", "jpg", "jpeg", "jpeg", "jpg", "jpg", "jpeg", "jpeg"]}