{"s": "Commiphora schlechteri", "c": "['ZA', 'MZ']", "n": ["53449686", "59719672", "59719679", "59719683", "59719688", "59719690", "59719694", "59719698", "65476296", "65476298"], "r": ["Troos van der Merwe", "Francois du Randt", "Francois du Randt", "Francois du Randt", "Francois du Randt", "Francois du Randt", "Francois du Randt", "Francois du Randt", "Francois du Randt", "Francois du Randt"], "l": ["CC BY-NC 4.0", "CC BY-NC 4.0", "CC BY-NC 4.0", "CC BY-NC 4.0", "CC BY-NC 4.0", "CC BY-NC 4.0", "CC BY-NC 4.0", "CC BY-NC 4.0", "CC BY-NC 4.0", "CC BY-NC 4.0"], "i": ["jpg", "jpg", "jpg", "jpg", "jpg", "jpg", "jpg", "jpg", "jpg", "jpg"]}