{"s": "Schenkia australis", "c": "['AU']", "n": ["242609423", "242609427", "243082106", "243082118", "246196544", "246196556", "246196770", "246196782", "246196788", "246337727"], "r": ["Martin Bennett", "Martin Bennett", "Gary", "Gary", "Jenny Emeny", "Jenny Emeny", "Jenny Emeny", "Jenny Emeny", "Jenny Emeny", "Martin Bennett"], "l": ["CC BY-NC 4.0", "CC BY-NC 4.0", "CC BY-NC 4.0", "CC BY-NC 4.0", "CC BY-NC 4.0", "CC BY-NC 4.0", "CC BY-NC 4.0", "CC BY-NC 4.0", "CC BY-NC 4.0", "CC BY-NC 4.0"], "i": ["jpeg", "jpeg", "jpg", "jpg", "jpeg", "jpeg", "jpeg", "jpeg", "jpeg", "jpeg"]}