{"s": "Baccharis brachylaenoides", "c": "['CO']", "n": ["78938914", "78938960", "79348560", "79348569", "106606210", "106605806", "106605720", "106606126", "106606026", "106605905"], "r": ["humbertomendozacifuentes", "humbertomendozacifuentes", "humbertomendozacifuentes", "humbertomendozacifuentes", "Apipa", "Apipa", "Apipa", "Apipa", "Apipa", "Apipa"], "l": ["CC BY-NC 4.0", "CC BY-NC 4.0", "CC BY-NC 4.0", "CC BY-NC 4.0", "CC BY-NC 4.0", "CC BY-NC 4.0", "CC BY-NC 4.0", "CC BY-NC 4.0", "CC BY-NC 4.0", "CC BY-NC 4.0"], "i": ["jpg", "jpg", "jpg", "jpg", "jpeg", "jpeg", "jpeg", "jpeg", "jpeg", "jpeg"]}