{"s": "Sebastiania commersoniana", "c": "['UY', 'BR', 'AR']", "n": ["156129698", "74951504", "199482877", "244375390", "159002155", "289378031", "289377963", "246132683", "246140961", "246140915"], "r": ["Lucas Villafa\u00f1e", "Mat\u00edas Zarucki", "alcira8", "Facundo Chieffo", "laauroradelpalmar", "Canelones Sustentable", "Canelones Sustentable", "Maximiliano Leo", "vinicius_s_domingues", "vinicius_s_domingues"], "l": ["CC BY-NC 4.0", "CC BY-NC 4.0", "CC BY 4.0", "CC BY 4.0", "CC BY-NC 4.0", "CC BY-NC 4.0", "CC BY-NC 4.0", "CC BY-NC 4.0", "CC BY-SA 4.0", "CC BY-SA 4.0"], "i": ["jpg", "jpeg", "jpeg", "jpg", "jpg", "jpeg", "jpeg", "jpeg", "jpeg", "jpeg"]}