{"s": "Manihot walkerae", "c": "['US']", "n": ["284583409", "284583573", "284583289", "284583197", "284583016", "284583496", "284584009", "284584115", "284584246", "241477632"], "r": ["Reid Hardin", "Reid Hardin", "Reid Hardin", "Reid Hardin", "Reid Hardin", "Reid Hardin", "Reid Hardin", "Reid Hardin", "Reid Hardin", "Joey Santore"], "l": ["CC BY-NC 4.0", "CC BY-NC 4.0", "CC BY-NC 4.0", "CC BY-NC 4.0", "CC BY-NC 4.0", "CC BY-NC 4.0", "CC BY-NC 4.0", "CC BY-NC 4.0", "CC BY-NC 4.0", "CC BY-NC 4.0"], "i": ["jpeg", "jpeg", "jpeg", "jpeg", "jpeg", "jpeg", "jpeg", "jpeg", "jpeg", "jpeg"]}