{"s": "Crataegus rhipidophylla", "c": "['RU', 'DE', 'SE', 'LT', 'PL', 'BY', 'CH', 'UA']", "n": ["284580755", "198812754", "115405634", "115405694", "285640861", "285640894", "321651304", "321651331", "321651363", "321651398"], "r": ["polinastefaniuk", "Alexander Baransky", "Anastasia Davydova", "Anastasia Davydova", "winterling", "winterling", "winterling", "winterling", "winterling", "winterling"], "l": ["CC BY-NC 4.0", "CC BY-NC 4.0", "CC BY-NC 4.0", "CC BY-NC 4.0", "CC BY-NC 4.0", "CC BY-NC 4.0", "CC BY-NC 4.0", "CC BY-NC 4.0", "CC BY-NC 4.0", "CC BY-NC 4.0"], "i": ["jpeg", "jpg", "jpeg", "jpeg", "jpeg", "jpeg", "jpeg", "jpeg", "jpeg", "jpeg"]}