{"s": "Anopterus glandulosus", "c": "['AU']", "n": ["242262621", "669689", "676375", "242767074", "242767085", "242767089", "242939445", "242939463", "242939479", "116052110"], "r": ["Nick Fitzgerald", "Christopher Tracey", "Christopher Tracey", "Wendy Baiguerra", "Wendy Baiguerra", "Wendy Baiguerra", "Iona", "Iona", "Iona", "Luke Cooper"], "l": ["CC BY-NC 4.0", "CC BY-NC-SA 4.0", "CC BY-NC-SA 4.0", "CC BY-NC 4.0", "CC BY-NC 4.0", "CC BY-NC 4.0", "CC BY-NC 4.0", "CC BY-NC 4.0", "CC BY-NC 4.0", "CC BY-NC 4.0"], "i": ["jpeg", "JPG", "JPG", "jpg", "jpg", "jpg", "jpeg", "jpeg", "jpeg", "jpeg"]}