{"s": "Cucurbita pedatifolia", "c": "['MX']", "n": ["156309325", "156309367", "2938079", "2938080", "3955843", "4121239", "82744691", "82744672", "88370027", "88370157"], "r": ["Edgar Pedro M\u00e9ndez V\u00e1zquez", "Edgar Pedro M\u00e9ndez V\u00e1zquez", "Pedro N\u00e1jera Quezada", "Pedro N\u00e1jera Quezada", "Pedro N\u00e1jera Quezada", "Jos\u00e9 Belem Hern\u00e1ndez D\u00edaz", "julyoeh", "julyoeh", "Aure G", "Aure G"], "l": ["CC BY-NC 4.0", "CC BY-NC 4.0", "CC BY-NC 4.0", "CC BY-NC 4.0", "CC BY-NC 4.0", "CC BY 4.0", "CC BY-NC 4.0", "CC BY-NC 4.0", "CC BY-NC 4.0", "CC BY-NC 4.0"], "i": ["jpeg", "jpeg", "JPG", "JPG", "JPG", "jpg", "jpeg", "jpeg", "jpg", "jpg"]}