{"s": "Hakea ulicina", "c": "['AU']", "n": ["156028382", "156051479", "156051499", "156051521", "74916025", "74919855", "74919859", "74921357", "74926727", "74926729"], "r": ["angeladunn07", "ron_willemsen", "ron_willemsen", "ron_willemsen", "Chris Clarke", "Chris Clarke", "Chris Clarke", "Chris Clarke", "Chris Clarke", "Chris Clarke"], "l": ["CC BY-NC 4.0", "CC BY-NC 4.0", "CC BY-NC 4.0", "CC BY-NC 4.0", "CC BY 4.0", "CC BY 4.0", "CC BY 4.0", "CC BY 4.0", "CC BY 4.0", "CC BY 4.0"], "i": ["jpg", "jpg", "jpg", "jpg", "jpeg", "jpeg", "jpeg", "jpeg", "jpeg", "jpeg"]}