{"s": "Schizopepon bryoniifolius", "c": "['KR', 'JP', 'RU']", "n": ["241542721", "242086129", "242086337", "289562544", "51209550", "51210117", "51210141", "51210155", "51210197", "51210355"], "r": ["Lisa Petersson", "Tatjana Koroteeva", "Tatjana Koroteeva", "sergey_stefanov", "Gularjanz Grigoryi Mihajlovich", "Gularjanz Grigoryi Mihajlovich", "Gularjanz Grigoryi Mihajlovich", "Gularjanz Grigoryi Mihajlovich", "Gularjanz Grigoryi Mihajlovich", "Gularjanz Grigoryi Mihajlovich"], "l": ["CC BY-NC 4.0", "CC BY-NC 4.0", "CC BY-NC 4.0", "CC BY-NC 4.0", "CC BY-NC 4.0", "CC BY-NC 4.0", "CC BY-NC 4.0", "CC BY-NC 4.0", "CC BY-NC 4.0", "CC BY-NC 4.0"], "i": ["jpg", "jpeg", "jpeg", "jpeg", "jpeg", "jpeg", "jpeg", "jpeg", "jpeg", "jpeg"]}