{"s": "Bessera elegantissima", "c": "['MX']", "n": ["156572869", "302644745", "302644932", "302833543", "304187326", "304187375", "305279894", "306561914", "305280635", "305303260"], "r": ["Styv De Jes\u00fas Calva", "rodrigodiego", "rodrigodiego", "rodrigodiego", "Abraham S\u00e1nchez Romero", "Abraham S\u00e1nchez Romero", "Ulises Pinedo", "Ulises Pinedo", "Ulises Pinedo", "Ulises Pinedo"], "l": ["CC BY-NC 4.0", "CC BY-NC 4.0", "CC BY-NC 4.0", "CC BY-NC 4.0", "CC BY 4.0", "CC BY 4.0", "CC BY 4.0", "CC BY 4.0", "CC BY 4.0", "CC BY 4.0"], "i": ["jpeg", "jpeg", "jpeg", "jpeg", "jpeg", "jpeg", "jpeg", "jpeg", "jpeg", "jpeg"]}