{"s": "Rhododendron multiflorum", "c": "['JP']", "n": ["43432184", "43432209", "45125659", "297675409", "297675847", "225227257", "225227239", "225227282", "225227300"], "r": ["\u5800\u5185\u4f38\u4e00", "\u5800\u5185\u4f38\u4e00", "sanyasou", "belvedere04", "belvedere04", "Yoshihiro Tokue", "Yoshihiro Tokue", "Yoshihiro Tokue", "Yoshihiro Tokue"], "l": ["CC BY-NC 4.0", "CC BY-NC 4.0", "CC BY-NC 4.0", "CC BY-NC 4.0", "CC BY-NC 4.0", "CC BY-NC 4.0", "CC BY-NC 4.0", "CC BY-NC 4.0", "CC BY-NC 4.0"], "i": ["jpeg", "jpeg", "jpg", "jpeg", "jpeg", "jpeg", "jpeg", "jpeg", "jpeg"]}