{"s": "Androsace villosa", "c": "['RS', 'GR', 'RU', 'TR', 'HR', 'ME', 'IT', 'CH', 'ES', 'SI', 'UA', 'BA', 'AT', 'AM', 'FR', 'BG', 'GE', 'RO', 'SK']", "n": ["114658891", "198562789", "284929807", "74935201", "285179059", "156483643", "115226032", "115228817", "115228818", "115228842"], "r": ["Todd Boland", "Sara G. Robinson", "Mike Moore", "Rino", "cindydepuniet", "pilararevalogamez", "mallaliev", "mallaliev", "mallaliev", "mallaliev"], "l": ["CC BY-NC 4.0", "CC BY-NC 4.0", "CC BY-NC 4.0", "CC BY-NC 4.0", "CC BY-NC 4.0", "CC BY-NC 4.0", "CC BY-NC 4.0", "CC BY-NC 4.0", "CC BY-NC 4.0", "CC BY-NC 4.0"], "i": ["jpeg", "jpeg", "jpg", "jpg", "jpg", "jpg", "jpg", "jpg", "jpg", "jpg"]}