{"s": "Scutellaria macra", "c": "['MX']", "n": ["116122289", "116122173", "116122204", "116122712", "163300452", "228257371", "228257476", "113762946", "113763131", "113763240"], "r": ["R.E.Llanos", "R.E.Llanos", "R.E.Llanos", "R.E.Llanos", "R.E.Llanos", "Sarah\u00ed D\u00edaz", "Sarah\u00ed D\u00edaz", "R.E.Llanos", "R.E.Llanos", "R.E.Llanos"], "l": ["CC BY-NC-SA 4.0", "CC BY-NC-SA 4.0", "CC BY-NC-SA 4.0", "CC BY-NC-SA 4.0", "CC BY-NC-SA 4.0", "CC BY-NC 4.0", "CC BY-NC 4.0", "CC BY-NC-SA 4.0", "CC BY-NC-SA 4.0", "CC BY-NC-SA 4.0"], "i": ["jpg", "jpg", "jpg", "jpg", "jpg", "jpeg", "jpeg", "jpg", "jpg", "jpg"]}