{"s": "Leonurus japonicus", "c": "['US', 'VI', 'BR', 'TW', 'NI', 'HK', 'PE', 'HN', 'RU', 'KR', 'NL', 'AU', 'DO', 'MX', 'PR', 'RE', 'AR', 'CR', 'BO', 'CN', 'MY', 'VE', 'CU', 'JP', 'HT']", "n": ["36464559", "36465132", "36465222", "36465293", "156597753", "242241954", "242243197", "242243201", "37354263", "115514506"], "r": ["William Wimley", "William Wimley", "William Wimley", "William Wimley", "Ruth Guti\u00e9rrez Oliveros", "Carlos Schmidtutz", "Carlos Schmidtutz", "Carlos Schmidtutz", "veronikmoon", "Leonardo Adri\u00e1n LEIVA"], "l": ["CC BY-NC 4.0", "CC BY-NC 4.0", "CC BY-NC 4.0", "CC BY-NC 4.0", "CC0 1.0", "CC BY-NC 4.0", "CC BY-NC 4.0", "CC BY-NC 4.0", "CC BY-NC 4.0", "CC BY-NC 4.0"], "i": ["jpg", "jpg", "jpg", "jpg", "jpeg", "jpeg", "jpeg", "jpeg", "jpg", "jpg"]}