{"s": "Polygala myrtifolia", "c": "['ES', 'PT', 'US', 'AR', 'FR', 'MT', 'TR', 'AU', 'GR', 'ZA', 'MA', 'IT', 'TN', 'UY', 'CL', 'CO', 'NF', 'NZ']", "n": ["241389909", "241469409", "241469369", "241469351", "241497272", "284716016", "284716964", "156017039", "76688194", "156106102"], "r": ["Nanna Joubert", "Charleen", "Charleen", "Charleen", "Onebianca", "Richard J. Buist", "Richard J. Buist", "charlienature", "benkhlen", "Matt Berger"], "l": ["CC BY-NC 4.0", "CC BY-NC 4.0", "CC BY-NC 4.0", "CC BY-NC 4.0", "CC BY-NC 4.0", "CC BY-NC 4.0", "CC BY-NC 4.0", "CC BY-NC 4.0", "CC BY-NC 4.0", "CC BY 4.0"], "i": ["jpeg", "jpeg", "jpeg", "jpeg", "jpg", "jpg", "jpg", "jpeg", "jpg", "jpg"]}