{"s": "Blumea balsamifera", "c": "['MY', 'PH', 'ID', 'TH', 'TW', 'HK']", "n": ["37663798", "37663803", "37663813", "37663817", "37663821", "37663828", "75643226", "75642945", "242956727", "242956736"], "r": ["sugumaran", "sugumaran", "sugumaran", "sugumaran", "sugumaran", "sugumaran", "\u5229\u627f\u62d4", "\u5229\u627f\u62d4", "\u9ec3\u7f8e\u6eff", "\u9ec3\u7f8e\u6eff"], "l": ["CC BY-NC 4.0", "CC BY-NC 4.0", "CC BY-NC 4.0", "CC BY-NC 4.0", "CC BY-NC 4.0", "CC BY-NC 4.0", "CC BY-NC 4.0", "CC BY-NC 4.0", "CC BY 4.0", "CC BY 4.0"], "i": ["jpeg", "jpeg", "jpeg", "jpeg", "jpeg", "jpeg", "jpeg", "jpeg", "jpg", "jpg"]}