{"s": "Oedera sedifolia", "c": "['ZA']", "n": ["156695440", "156695417", "156695390", "156695376", "156695474", "156695476", "157762566", "157762595", "157762702", "157762775"], "r": ["Nicola van Berkel", "Nicola van Berkel", "Nicola van Berkel", "Nicola van Berkel", "Nicola van Berkel", "Nicola van Berkel", "Joey Santore", "Joey Santore", "Joey Santore", "Joey Santore"], "l": ["CC BY-SA 4.0", "CC BY-SA 4.0", "CC BY-SA 4.0", "CC BY-SA 4.0", "CC BY-SA 4.0", "CC BY-SA 4.0", "CC BY-NC 4.0", "CC BY-NC 4.0", "CC BY-NC 4.0", "CC BY-NC 4.0"], "i": ["jpeg", "jpeg", "jpeg", "jpeg", "jpeg", "jpeg", "jpeg", "jpeg", "jpeg", "jpeg"]}