{"s": "Cirsium clavatum", "c": "['US']", "n": ["85153365", "211880588", "211880613", "211880634", "212940997", "212941017", "212941033", "171813451", "171813464", "171813533"], "r": ["z432", "Zachary Nielsen", "Zachary Nielsen", "Zachary Nielsen", "Lilly Setters", "Lilly Setters", "Lilly Setters", "Andrey Zharkikh", "Andrey Zharkikh", "Andrey Zharkikh"], "l": ["CC BY-NC 4.0", "CC BY-NC 4.0", "CC BY-NC 4.0", "CC BY-NC 4.0", "CC BY-NC 4.0", "CC BY-NC 4.0", "CC BY-NC 4.0", "CC BY-NC 4.0", "CC BY-NC 4.0", "CC BY-NC 4.0"], "i": ["jpg", "jpg", "jpg", "jpg", "jpg", "jpg", "jpg", "jpg", "jpg", "jpg"]}