{"s": "Neoregelia pauciflora", "c": "['BR']", "n": ["244371817", "244371866", "244371947", "247246030", "252244346", "252244343", "252244349", "46385704", "232022387"], "r": ["Claudio Novaes", "Claudio Novaes", "Claudio Novaes", "prairieboy", "MAYKOL HOFFMANN SILVA", "MAYKOL HOFFMANN SILVA", "MAYKOL HOFFMANN SILVA", "Gabrielly Benaducci Tolentino", "Gabriel Bonfa"], "l": ["CC BY-NC 4.0", "CC BY-NC 4.0", "CC BY-NC 4.0", "CC BY-NC 4.0", "CC BY-NC 4.0", "CC BY-NC 4.0", "CC BY-NC 4.0", "CC BY-NC 4.0", "CC BY-NC 4.0"], "i": ["jpg", "jpg", "jpg", "jpg", "jpeg", "jpeg", "jpeg", "jpg", "jpeg"]}