{"s": "Peganum mexicanum", "c": "['US', 'MX']", "n": ["36564117", "36564222", "36564338", "36564483", "37276229", "37276709", "37278885", "37690628", "118147472", "118147447"], "r": ["Daniel", "Daniel", "Daniel", "Daniel", "marinog", "marinog", "marinog", "Carlos G Velazco-Macias", "Kevin Meza", "Kevin Meza"], "l": ["CC BY-NC 4.0", "CC BY-NC 4.0", "CC BY-NC 4.0", "CC BY-NC 4.0", "CC BY-NC 4.0", "CC BY-NC 4.0", "CC BY-NC 4.0", "CC BY-NC 4.0", "CC BY-NC 4.0", "CC BY-NC 4.0"], "i": ["jpeg", "jpeg", "jpeg", "jpeg", "jpeg", "jpeg", "jpeg", "jpg", "jpeg", "jpeg"]}