{"s": "Lithraea brasiliensis", "c": "['BR', 'UY']", "n": ["74580281", "198515440", "241867964", "241867987", "244001339", "244001356", "244001388", "76801213", "76801235", "244832348"], "r": ["Noelia", "JG", "Andr\u00e9s Fern\u00e1ndez", "Andr\u00e9s Fern\u00e1ndez", "Ben Costamagna", "Ben Costamagna", "Ben Costamagna", "Mat\u00edas Zarucki", "Mat\u00edas Zarucki", "Elena Ferreira"], "l": ["CC BY 4.0", "CC BY 4.0", "CC BY-NC 4.0", "CC BY-NC 4.0", "CC BY-NC 4.0", "CC BY-NC 4.0", "CC BY-NC 4.0", "CC BY-NC 4.0", "CC BY-NC 4.0", "CC BY-NC 4.0"], "i": ["jpeg", "jpeg", "jpg", "jpg", "jpeg", "jpeg", "jpeg", "jpeg", "jpeg", "jpeg"]}