{"s": "Gentianella azurea", "c": "['CN', 'RU', 'MN', 'KG']", "n": ["116150726", "121734071", "121735356", "121735384", "171725970", "223170277", "222976352", "313857088", "315616471", "315616538"], "r": ["Pyak Andrei", "tsengell", "tsengell", "tsengell", "Chao Shi", "\u8c73\u98ce", "\u8c73\u98ce", "Terry Townshend", "B.Byambajav", "B.Byambajav"], "l": ["CC BY-NC 4.0", "CC BY-NC 4.0", "CC BY-NC 4.0", "CC BY-NC 4.0", "CC0 1.0", "CC BY-NC 4.0", "CC BY-NC 4.0", "CC BY-NC 4.0", "CC BY-NC 4.0", "CC BY-NC 4.0"], "i": ["jpeg", "jpeg", "jpeg", "jpeg", "jpg", "jpeg", "jpeg", "jpeg", "jpg", "jpg"]}