{"s": "Thelocactus bicolor", "c": "['MX', 'US']", "n": ["286619955", "286625948", "286655251", "286655301", "286655364", "287254644", "287254805", "287254831", "287254862", "287254973"], "r": ["johnyochum", "johnyochum", "elisamarivera", "elisamarivera", "elisamarivera", "Mauricio Calder\u00f3n", "Mauricio Calder\u00f3n", "Mauricio Calder\u00f3n", "Mauricio Calder\u00f3n", "Mauricio Calder\u00f3n"], "l": ["CC BY 4.0", "CC BY 4.0", "CC BY-NC 4.0", "CC BY-NC 4.0", "CC BY-NC 4.0", "CC BY-NC 4.0", "CC BY-NC 4.0", "CC BY-NC 4.0", "CC BY-NC 4.0", "CC BY-NC 4.0"], "i": ["jpeg", "jpeg", "jpeg", "jpeg", "jpeg", "jpeg", "jpeg", "jpeg", "jpeg", "jpeg"]}